skm_tea/__init__.py
skm_tea/callbacks/__init__.py
skm_tea/callbacks/checkpoint.py
skm_tea/config/__init__.py
skm_tea/config/defaults.py
skm_tea/data/__init__.py
skm_tea/data/collate.py
skm_tea/data/data_module.py
skm_tea/data/dataset.py
skm_tea/data/register.py
skm_tea/data/transform.py
skm_tea/engine/__init__.py
skm_tea/engine/defaults.py
skm_tea/engine/model_zoo.py
skm_tea/engine/trainer.py
skm_tea/engine/modules/__init__.py
skm_tea/engine/modules/base.py
skm_tea/engine/modules/module.py
skm_tea/engine/modules/recon.py
skm_tea/evaluation/__init__.py
skm_tea/evaluation/qdess_evaluation.py
skm_tea/losses/__init__.py
skm_tea/losses/build.py
skm_tea/losses/loss_computer.py
skm_tea/losses/seg_losses.py
skm_tea/metrics/__init__.py
skm_tea/metrics/qmri.py
skm_tea/modeling/__init__.py
skm_tea/modeling/build.py
skm_tea/modeling/monai_nets.py
skm_tea/utils/__init__.py
skm_tea/utils/env.py
skm_tea/utils/general.py
skm_tea/utils/path.py
skm_tea/utils/pl_utils.py
skm_tea/utils/visualizer.py
skm_tea-0.0.3.dist-info/LICENSE
skm_tea-0.0.3.dist-info/METADATA
skm_tea-0.0.3.dist-info/WHEEL
skm_tea-0.0.3.dist-info/top_level.txt
skm_tea-0.0.3.dist-info/RECORD
