Metadata-Version: 2.1
Name: skm-tea
Version: 0.0.3
Summary: A package for interacting with, visualizing, and benchmarking the SKM-TEA dataset
Home-page: https://github.com/StanfordMIMI/skm-tea
Author: The SKM-TEA Team
Author-email: arjundd@stanford.edu
License: UNKNOWN
Platform: UNKNOWN
Classifier: Programming Language :: Python :: 3
Classifier: License :: OSI Approved :: MIT License
Classifier: Operating System :: OS Independent
Classifier: Topic :: Scientific/Engineering :: Artificial Intelligence
Requires-Python: >=3.6
License-File: LICENSE
Requires-Dist: h5py
Requires-Dist: matplotlib
Requires-Dist: numpy
Requires-Dist: fvcore
Requires-Dist: dosma (>=0.1.0)
Requires-Dist: iopath
Requires-Dist: medpy
Requires-Dist: packaging
Requires-Dist: pandas
Requires-Dist: tqdm (>=4.42.0)
Requires-Dist: xlrd
Requires-Dist: monai (>=0.3.0)
Requires-Dist: meddlr (>=0.0.5)
Requires-Dist: pytorch-lightning (<1.8.0,>=1.0.0)
Requires-Dist: zarr
Provides-Extra: dev
Requires-Dist: coverage ; extra == 'dev'
Requires-Dist: flake8 ; extra == 'dev'
Requires-Dist: isort ; extra == 'dev'
Requires-Dist: black (==22.3.0) ; extra == 'dev'
Requires-Dist: flake8-bugbear ; extra == 'dev'
Requires-Dist: flake8-comprehensions ; extra == 'dev'
Requires-Dist: pre-commit (>=2.9.3) ; extra == 'dev'
Requires-Dist: medpy ; extra == 'dev'
Requires-Dist: pooch ; extra == 'dev'
Requires-Dist: gdown ; extra == 'dev'
Requires-Dist: sphinx ; extra == 'dev'
Requires-Dist: sphinxcontrib-bibtex ; extra == 'dev'
Requires-Dist: sphinx-rtd-theme ; extra == 'dev'
Requires-Dist: m2r2 ; extra == 'dev'
